__init__.py
csa2sfen.py
csa2sfen-1.0.0.dist-info/METADATA
csa2sfen-1.0.0.dist-info/WHEEL
csa2sfen-1.0.0.dist-info/top_level.txt
csa2sfen-1.0.0.dist-info/RECORD
