Metadata-Version: 2.1
Name: csa2sfen
Version: 1.0.0
Summary: 将棋の棋譜のcsa形式をsfen形式に変換するパッケージ
Home-page: https://github.com/ryicoh/csa2sfen
Author: ryicoh
Author-email: ryicoh@gmail.com
License: MIT License
Keywords: shogi,csa,sfen3
Platform: UNKNOWN
Classifier: Development Status :: 5 - Production/Stable
Classifier: License :: OSI Approved :: BSD License
Classifier: Programming Language :: Python
Classifier: Programming Language :: Python :: 3
Classifier: Programming Language :: Python :: 3.4
Classifier: Programming Language :: Python :: 3.5
Classifier: Programming Language :: Python :: 3.6
Classifier: Topic :: Database
Classifier: Topic :: Software Development :: Libraries :: Python Modules
Requires-Dist: python-shogi (==1.0.14)
